ultimate/README.md
ultimate/__init__.py
ultimate/conlib.py
ultimate/mesh.dll.2
ultimate/mesh.py
ultimate/mesh.so.2
ultimate/mlp.py
ultimate/plotting.py
ultimate/progress.py
ultimate-2.75.2.dist-info/METADATA
ultimate-2.75.2.dist-info/WHEEL
ultimate-2.75.2.dist-info/top_level.txt
ultimate-2.75.2.dist-info/RECORD
