Metadata-Version: 2.1
Name: ultimate
Version: 2.75.2
Summary: A scikit-learn compatible neural network implementation
Home-page: https://pypi.org/project/ultimate/
Author: anycode
Author-email: anycode@yahoo.com
Maintainer: anycode
Maintainer-email: anycode@yahoo.com
License: UNKNOWN
Platform: all
Classifier: License :: OSI Approved :: GNU Affero General Public License v3
Classifier: Operating System :: OS Independent
Classifier: Intended Audience :: Developers
Classifier: Programming Language :: Python
Classifier: Programming Language :: Python :: 2
Classifier: Programming Language :: Python :: 3
Classifier: Topic :: Software Development :: Libraries
